devcluster/__init__.py
devcluster/__main__.py
devcluster/atomic.py
devcluster/config.py
devcluster/console.py
devcluster/devcluster.py
devcluster/example.yaml
devcluster/logger.py
devcluster/net.py
devcluster/recovery.py
devcluster/stage.py
devcluster/state_machine.py
devcluster/util.py
devcluster-1.3.1.dist-info/LICENSE
devcluster-1.3.1.dist-info/METADATA
devcluster-1.3.1.dist-info/WHEEL
devcluster-1.3.1.dist-info/entry_points.txt
devcluster-1.3.1.dist-info/top_level.txt
devcluster-1.3.1.dist-info/RECORD
