Metadata-Version: 2.1
Name: devcluster
Version: 1.3.1
Summary: Developer tool for running the Determined cluster
Home-page: https://github.com/determined-ai/devcluster/
Author: Determined AI
Author-email: hello@determined.ai
License: Apache License 2.0
Platform: UNKNOWN
Classifier: License :: OSI Approved :: Apache Software License
Requires-Python: >=3.6
License-File: LICENSE
Requires-Dist: appdirs
Requires-Dist: pyyaml
Requires-Dist: setuptools ; python_version < "3.9"
